PKG-INFO
README.txt
pypi_upload.sh
setup.cfg
setup.py
collective/__init__.py
collective.transform.docbook.egg-info/PKG-INFO
collective.transform.docbook.egg-info/SOURCES.txt
collective.transform.docbook.egg-info/dependency_links.txt
collective.transform.docbook.egg-info/entry_points.txt
collective.transform.docbook.egg-info/namespace_packages.txt
collective.transform.docbook.egg-info/not-zip-safe
collective.transform.docbook.egg-info/requires.txt
collective.transform.docbook.egg-info/top_level.txt
collective/transform/__init__.py
collective/transform/docbook/README.txt
collective/transform/docbook/__init__.py
collective/transform/docbook/configure.zcml
collective/transform/docbook/html_to_docbook.py
collective/transform/docbook/mimetype.py
collective/transform/docbook/setuphandlers.py
collective/transform/docbook/tests.py
collective/transform/docbook/version.txt
collective/transform/docbook/profiles/default/collective.transform.docbook-default.txt
collective/transform/docbook/profiles/uninstall/collective.transform.docbook-uninstall.txt
docs/HISTORY.txt
docs/INSTALL.txt
docs/LICENSE.GPL
docs/LICENSE.txt