Metadata-Version: 1.0
Name: collective.transform.docbook
Version: 0.1
Summary: DocBook text transform for Plone
Home-page: https://svn.plone.org/svn/collective/collective.transform.docbook
Author: Timo Stollenwerk
Author-email: timo@zmag.de
License: GPL
Platform: UNKNOWN
Classifier: Framework :: Plone
Classifier: Programming Language :: Python
Classifier: Topic :: Software Development :: Libraries :: Python Modules
